flux_led/__init__.py
flux_led/aio.py
flux_led/aiodevice.py
flux_led/aioprotocol.py
flux_led/aioscanner.py
flux_led/aioutils.py
flux_led/base_device.py
flux_led/const.py
flux_led/device.py
flux_led/fluxled.py
flux_led/models_db.py
flux_led/pattern.py
flux_led/protocol.py
flux_led/py.typed
flux_led/scanner.py
flux_led/sock.py
flux_led/timer.py
flux_led/utils.py
flux_led-1.1.4.dist-info/LICENSE
flux_led-1.1.4.dist-info/METADATA
flux_led-1.1.4.dist-info/WHEEL
flux_led-1.1.4.dist-info/entry_points.txt
flux_led-1.1.4.dist-info/top_level.txt
flux_led-1.1.4.dist-info/RECORD
